git_open/__init__.py
git_open/cli.py
git_open/git_open.py
git_open-1.3.0.dist-info/LICENSE
git_open-1.3.0.dist-info/METADATA
git_open-1.3.0.dist-info/WHEEL
git_open-1.3.0.dist-info/entry_points.txt
git_open-1.3.0.dist-info/top_level.txt
git_open-1.3.0.dist-info/RECORD
