Metadata-Version: 2.1
Name: git-open
Version: 1.3.0
Summary: Open a git repo in the browser from the terminal.
Home-page: https://github.com/cfp2000/git-open
Author: 
Author-email: cfp@highball.se
Maintainer: 
Maintainer-email: cfp@highball.se
License: GPLv3
Project-URL: Bug Tracker, https://github.com/cfp2000/git-open/issues
Project-URL: Source Code, https://github.com/cfp2000/git-open
Keywords: terminal,git,web
Classifier: Development Status :: 5 - Production/Stable
Classifier: Intended Audience :: Developers
Classifier: Natural Language :: English
Classifier: License :: OSI Approved :: GNU General Public License v3 (GPLv3)
Classifier: Operating System :: OS Independent
Classifier: Programming Language :: Python
Classifier: Programming Language :: Python :: 3.9
Classifier: Programming Language :: Python :: Implementation :: CPython
Classifier: Topic :: Utilities
License-File: LICENSE
Requires-Dist: Click (>=6.7)
Requires-Dist: sh (>=1.12.14)
Requires-Dist: six (>=1.11.0)
Provides-Extra: dev
Requires-Dist: pytest ; extra == 'dev'
Requires-Dist: coverage ; extra == 'dev'
Requires-Dist: flake8 ; extra == 'dev'
Requires-Dist: six ; extra == 'dev'
Requires-Dist: sphinx ; extra == 'dev'
Requires-Dist: pre-commit ; extra == 'dev'
Provides-Extra: docs
Requires-Dist: sphinx ; extra == 'docs'
Provides-Extra: setup
Requires-Dist: wheel ; extra == 'setup'
Provides-Extra: tests
Requires-Dist: pytest ; extra == 'tests'
Requires-Dist: coverage ; extra == 'tests'
Requires-Dist: flake8 ; extra == 'tests'
Requires-Dist: six ; extra == 'tests'
